avpassgen/__init__.py
avpassgen/api.py
avpassgen/capture.py
avpassgen/cli.py
avpassgen/entropy.py
avpassgen/exceptions.py
avpassgen/password.py
avpassgen-0.1.1.dist-info/licenses/LICENSE
avpassgen-0.1.1.dist-info/METADATA
avpassgen-0.1.1.dist-info/WHEEL
avpassgen-0.1.1.dist-info/entry_points.txt
avpassgen-0.1.1.dist-info/top_level.txt
avpassgen-0.1.1.dist-info/RECORD
