Metadata-Version: 2.4
Name: avpassgen
Version: 0.1.1
Summary: Genera contraseñas a partir de entropía de audio/video en tiempo real, mezclada con el CSPRNG del sistema.
Author-email: Yeshua Chiliquinga <yeshuachiliquinga@gmail.com>
License: MIT
Classifier: Programming Language :: Python :: 3
Classifier: License :: OSI Approved :: MIT License
Classifier: Operating System :: OS Independent
Classifier: Intended Audience :: Developers
Classifier: Topic :: Security :: Cryptography
Classifier: Topic :: Utilities
Requires-Python: >=3.9
License-File: LICENSE
Requires-Dist: numpy>=1.22
Requires-Dist: cryptography>=41
Requires-Dist: opencv-python>=4.7
Requires-Dist: sounddevice>=0.4
Provides-Extra: cli
Requires-Dist: typer>=0.12.0; extra == "cli"
Dynamic: license-file
